pixelyai_core/__init__.py
pixelyai_core/client.py
pixelyai_core/engine_websocket/__init__.py
pixelyai_core/engine_websocket/client.py
pixelyai_core/engine_websocket/serve.py
pixelyai_core/prompt_templates/__init__.py
pixelyai_core/prompt_templates/chat/__init__.py
pixelyai_core/prompt_templates/chat/agnet.py
pixelyai_core/prompt_templates/chat/prompt.jinja2
pixelyai_core/prompt_templates/retrival_argumented_generation/__init__.py
pixelyai_core/prompt_templates/retrival_argumented_generation/agent.py
pixelyai_core/prompt_templates/retrival_argumented_generation/prompt.jinja2
pixelyai_core/serving/__init__.py
pixelyai_core/serving/engine_module.py
pixelyai_core-0.0.41.dist-info/LICENSE
pixelyai_core-0.0.41.dist-info/METADATA
pixelyai_core-0.0.41.dist-info/WHEEL
pixelyai_core-0.0.41.dist-info/top_level.txt
pixelyai_core-0.0.41.dist-info/RECORD
