Metadata-Version: 2.1
Name: pixelyai-core
Version: 0.0.41
Summary: PixelyAI Serve Engine
Author-email: Erfan Zare Chavoshi <Erfanzare810@gmail.com>
Project-URL: Homepage, https://github.com/erfanzar/PixelyAI
Project-URL: Issues, https://github.com/erfanzar/PixelyAI/issues
Project-URL: Documentation, https://erfanzar.github.io/PixelyAI
Classifier: Development Status :: 3 - Alpha
Classifier: Intended Audience :: Developers
Classifier: Topic :: Scientific/Engineering :: Artificial Intelligence
Classifier: License :: OSI Approved :: Apache Software License
Classifier: Programming Language :: Python :: 3
Classifier: Programming Language :: Python :: 3.8
Classifier: Programming Language :: Python :: 3.9
Classifier: Programming Language :: Python :: 3.10
Classifier: Programming Language :: Python :: 3.11
Classifier: Programming Language :: Python :: 3.12
Requires-Python: >=3.8
License-File: LICENSE
Requires-Dist: typing ~=3.7.4.3
Requires-Dist: ipython ~=8.17.2
Requires-Dist: tqdm ~=4.64.1
Requires-Dist: pydantic ==2.5.3
Requires-Dist: setuptools ~=68.1.2
Requires-Dist: gradio ~=4.18.0
Requires-Dist: numpy ~=1.26.2
Requires-Dist: uvicorn ~=0.23.2
Requires-Dist: fastapi ==0.110.1
Requires-Dist: pydantic-core ==2.14.6
Requires-Dist: requests ~=2.31.0
Requires-Dist: transformers >=4.36.1
Requires-Dist: huggingface-hub >=0.20.1
Requires-Dist: absl-py ==2.0.0
Requires-Dist: Jinja2 ~=3.1.2
Requires-Dist: agentx
